recurvedata/__init__.py
recurvedata/agent/__init__.py
recurvedata/agent/_version.py
recurvedata/agent/config.py
recurvedata/agent/exceptions.py
recurvedata/agent/utils.py
recurvedata/agent/_commands/__init__.py
recurvedata/agent/_commands/_typer.py
recurvedata/agent/_commands/agent.py
recurvedata/agent/_commands/config.py
recurvedata/agent/_commands/data.py
recurvedata/agent/_commands/main.py
recurvedata/agent/_commands/service.py
recurvedata/agent/_internal/__init__.py
recurvedata/agent/_internal/agent.py
recurvedata/agent/_internal/client.py
recurvedata/agent/_internal/docker.py
recurvedata/agent/_internal/host.py
recurvedata/agent/_internal/log_collector.py
recurvedata/agent/_internal/schemas.py
recurvedata/agent/_internal/service_loop.py
recurvedata/agent/_internal/task_executor.py
recurvedata/agent/_internal/task_logger.py
recurvedata/agent/_internal/task_manager.py
recurvedata/agent/_internal/utils.py
recurvedata/agent/_internal/worker.py
recurvedata/agent/_internal/worker_management.py
recurvedata/agent/_internal/cube/__init__.py
recurvedata/agent/_internal/cube/cube_utils.py
recurvedata/agent/_internal/cube/push_config.py
recurvedata/agent/_internal/cube/query_service.py
recurvedata/agent/_internal/cube/restart_service.py
recurvedata/agent/_internal/cube/certs/cacert.pem
recurvedata/agent/_internal/websocket/__init__.py
recurvedata/agent/_internal/websocket/callbacks.py
recurvedata/agent/_internal/websocket/connector.py
recurvedata/agent/_internal/websocket/enums.py
recurvedata/agent/_internal/websocket/message_handlers.py
recurvedata/agent/_internal/websocket/schemas.py
recurvedata/agent/dpserver/__init__.py
recurvedata/agent/dpserver/client.py
recurvedata/agent/dpserver/schema.py
reorc_agent-1.0.14.dist-info/METADATA
reorc_agent-1.0.14.dist-info/WHEEL
reorc_agent-1.0.14.dist-info/entry_points.txt
reorc_agent-1.0.14.dist-info/RECORD
