Metadata-Version: 2.4
Name: reorc-agent
Version: 1.0.14
Summary: Reorc Agent
Author-email: Reorc Team <contact@recurvedata.com>
Classifier: Development Status :: 5 - Production/Stable
Classifier: Intended Audience :: Developers
Classifier: Intended Audience :: Information Technology
Classifier: Intended Audience :: System Administrators
Classifier: Operating System :: POSIX :: Linux
Classifier: Programming Language :: Python
Classifier: Programming Language :: Python :: 3
Classifier: Programming Language :: Python :: 3 :: Only
Classifier: Programming Language :: Python :: 3.9
Classifier: Programming Language :: Python :: 3.10
Classifier: Programming Language :: Python :: 3.11
Classifier: Programming Language :: Python :: 3.12
Classifier: Topic :: Software Development
Requires-Dist: aiofiles
Requires-Dist: docker
Requires-Dist: httpx>=0.27.0
Requires-Dist: loguru
Requires-Dist: psutil
Requires-Dist: psycopg2-binary
Requires-Dist: pydantic>=2
Requires-Dist: tenacity
Requires-Dist: typer>=0.12.3
Requires-Dist: websockets>=15.0.1
